Workbook

Sheet README
A1: Michigan LTC Network — Reconciled Financial Model (FINAL working)
A2: Base case (fuel + carbon black) anchors the headline; RIN + Section 45Z shown separately as contingent upside. Yellow = editable inputs. Green = defensible base. Orange = contingent. Date 2026-06-03. Not financial/legal/tax advice.
A5: THE RECONCILIATION (why this model)
A6: The signed WasteWerx Model 3 headline (~$35.58M rev / ~$30.2M EBITDA per site) depends on ~$20.4M of
A7: RIN + Section 45Z credits that are NOT secured (registration, eligibility, monetization, counsel/tax review
A8: all required). This model anchors a DEFENSIBLE base case and shows credits separately as contingent upside.
A10: HOW TO READ
A11: Per_Site - line-by-line revenue build-up + 4 scenarios (conservative base, upgraded base, signed headline,
A12: full stack) with EBITDA each, and the per-site capital bridge.
A13: Network - 3-site rollup.
A14: Raises - $15M/site project raise + use-of-funds reconciliation; separate $2.5M company raise.
A15: Caveats - what must be confirmed / reviewed before any investor-facing use.
... A25: * Figures trace to the canonical workbook / signed pro forma; verify before circulation.

Sheet Inputs
A1: Inputs — editable assumptions (per site)
A2: Edit yellow cells; everything else recalculates. [CONFIRM] = verify before investor use.
A4: Key | B4: Assumption | C4: Value | D4: Unit | E4: Source / note
A5: tpd | B5: Feedstock throughput | C5: 100 | D5: MT/day | E5: WasteWerx model
A6: days | B6: Operating days | C6: 300 | D6: days/yr | E6: WasteWerx model
A7: oil_yield | B7: Oil/fuel yield | C7: 0.45 | D7: of feedstock | E7: WasteWerx model
A8: cb_yield | B8: Carbon black yield | C8: 0.45 | D8: of feedstock | E8: WasteWerx model
A9: oil_price | B9: Pyrolysis oil price (conservative/market) | C9: 500 | D9: $/MT | E9: market-grounded base [CONFIRM contract]
A10: cb_price | B10: Carbon black price | C10: 750 | D10: $/MT | E10: [CONFIRM market price + offtake]
A11: rd_rev | B11: Upgraded fuel: Renewable diesel revenue | C11: 4798080 | D11: $/yr | E11: signed Model 3 [requires distillation+offtake]
A12: saf_rev | B12: Upgraded fuel: SAF/kerosene revenue | C12: 10355040 | D12: $/yr | E12: signed Model 3 [CONFIRM product classification]
A13: d4_rin | B13: D4 RIN value (CONTINGENT) | C13: 4798080 | D13: $/yr | E13: signed Model 3 [RFS registration required]
A14: d7_rin | B14: D7 RIN value (CONTINGENT) | C14: 9204480 | D14: $/yr | E14: signed Model 3 [RFS registration required]
A15: z45_rd | B15: Section 45Z value - RD (CONTINGENT) | C15: 2399040 | D15: $/yr | E15: signed Model 3 [eligibility + tax counsel]
A16: z45_saf | B16: Section 45Z value - SAF (CONTINGENT) | C16: 4026960 | D16: $/yr | E16: signed Model 3 [eligibility + tax counsel]
... A37: sites | B37: Number of sites in network | C37: 3 | D37: # | E37: Michigan corridor

Sheet Opex_BuildUp
A1: Annual operating cost — bottom-up (per site, steady state)
A2: KEY FINDING: site labor ALONE exceeds the signed model's entire implied opex. Green = known, orange = estimate to confirm.
A4: Cost line | B4: Amount $/yr | C4: Status
A5: Site labor — loaded (62 FTE worst-case x MI-adj x cross-training) | B5: =Inputs!$C$17*Inputs!$C$18*Inputs!$C$19 | C5: WORST-CASE per WasteWerx (V.Tizio); benefits/MI rates need actuals [Robert]
A6: WasteWerx production royalty (recurring) | B6: =Inputs!$C$34 | C6: KNOWN — signed model
A7: WasteWerx monitoring fees (recurring) | B7: =Inputs!$C$33 | C7: KNOWN — signed model
A8: Net feedstock cost | B8: =Inputs!$C$20 | C8: [CONFIRM — may be tipping-fee positive]
A9: Utilities / energy (net of syngas self-supply) | B9: =Inputs!$C$21 | C9: ESTIMATE [CONFIRM]
A10: Maintenance materials + contract maintenance | B10: =Inputs!$C$22 | C10: ESTIMATE [CONFIRM]
A11: Insurance (industrial) | B11: =Inputs!$C$23 | C11: ESTIMATE [CONFIRM]
A12: Contracted services (security/janitorial/IT/3rd-party MRV) | B12: =Inputs!$C$24 | C12: NOT in staffing pro forma [CONFIRM]
A13: G&A / SG&A | B13: =Inputs!$C$25 | C13: ESTIMATE [CONFIRM]
A14: TOTAL ANNUAL OPEX (bottom-up) | B14: =SUM(B5:B13)
A16: Signed model's IMPLIED opex (rev - EBITDA) | B16: 5381149
A17: Understatement baked into signed EBITDA (bottom-up - implied) | B17: =B14-B16
A19: Labor ALONE (MI-adj x cross-training) | B19: =Inputs!$C$17*Inputs!$C$18*Inputs!$C$19
A20: -> at worst-case staffing, labor alone exceeds the signed model's entire implied opex. Signed EBITDA overstates margin.
A22: WasteWerx (V. Tizio, 5/27/26): staffing is intentional worst-case 'overkill'; cross-trained roles will reduce headcount;
A23: health insurance & benefits need actuals; salaries are FL market — Robert to adjust to Michigan pay rates. Flex via xtrain + mi_adj inputs.

Sheet Per_Site
A1: Per-site revenue build-up, scenarios & capital bridge
A2: Line-by-line build-up (the answer to 'show me $6.75M fuel -> $35.58M, line by line'). Base = green, contingent = orange.
A4: Revenue line | B4: Amount $/yr | C4: Category | D4: Status / caveat
A5: Pyrolysis oil — raw, market price | B5: =(Inputs!$C$5*Inputs!$C$6*Inputs!$C$7)*Inputs!$C$9 | C5: BASE (conservative) | D5: Market-grounded; most defensible
A6: Carbon black | B6: =(Inputs!$C$5*Inputs!$C$6*Inputs!$C$8)*Inputs!$C$10 | C6: BASE | D6: Real saleable product; excluded from signed model [CONFIRM price/offtake]
A7: Renewable diesel (upgraded fuel) | B7: =Inputs!$C$11 | C7: BASE (upgraded) | D7: Requires distillation refinery + offtake MOU
A8: SAF / kerosene (upgraded fuel) | B8: =Inputs!$C$12 | C8: BASE (upgraded) | D8: Requires distillation + offtake; [CONFIRM classification]
A9: D4 RIN | B9: =Inputs!$C$13 | C9: CONTINGENT UPSIDE | D9: RFS pathway registration required — NOT secured
A10: D7 RIN | B10: =Inputs!$C$14 | C10: CONTINGENT UPSIDE | D10: RFS pathway registration required — NOT secured
A11: Section 45Z — RD | B11: =Inputs!$C$15 | C11: CONTINGENT UPSIDE | D11: Eligibility + tax counsel required — NOT secured
A12: Section 45Z — SAF | B12: =Inputs!$C$16 | C12: CONTINGENT UPSIDE | D12: Eligibility + tax counsel required — NOT secured
A14: SCENARIO SUMMARY (per site)
A15: Scenario | B15: Revenue $/yr | C15: Opex $/yr | D15: EBITDA $/yr | E15: Credits in headline?
A16: Base — Conservative (raw oil + carbon black) | B16: =B5+B6 | C16: =Opex_BuildUp!$B$14 | D16: =B16-C16 | E16: No
A17: Base — Upgraded (RD + SAF + carbon black) | B17: =B7+B8+B6 | C17: =Opex_BuildUp!$B$14 | D17: =B17-C17 | E17: No
A18: Signed headline (RD + SAF + credits, no carbon black) | B18: =B7+B8+B9+B10+B11+B12 | C18: =Opex_BuildUp!$B$14 | D18: =B18-C18 | E18: YES — ~$20.4M credit-dependent
A19: Full stack (upgraded fuel + carbon black + credits) | B19: =B6+B7+B8+B9+B10+B11+B12 | C19: =Opex_BuildUp!$B$14 | D19: =B19-C19 | E19: YES
A21: Contingent credit value at risk in headline (RIN + 45Z) | B21: =B9+B10+B11+B12 | C21: <- this much of the signed headline is NOT secured
A23: PER-SITE CAPITAL BRIDGE
A24: Project raise per site | B24: =Inputs!$C$26
A25: WasteWerx Year 1 (license+design+monitoring+royalty) | B25: =Inputs!$C$31+Inputs!$C$32+Inputs!$C$33+Inputs!$C$34
A26: Customer-side capex | B26: =Inputs!$C$35
A27: Total Year 1 cash out | B27: =B25+B26
A28: Residual project envelope (land, civil, integration, contingency, payroll, reserves) | B28: =B24-B27
A30: Use-of-funds (sponsor rough) vs raise — RECONCILE
A31: Build + added construction + pre-processing + contingency | B31: =Inputs!$C$27+Inputs!$C$28+Inputs!$C$29+Inputs!$C$30
A32: Reconciliation gap vs $15M raise (negative = over) | B32: =Inputs!$C$26-B31 | C32: [CONFIRM which line absorbs the ~$1M]

Sheet Network
A1: Three-site network rollup (live x number of sites)
A2: Base anchors; credits flagged. Company raise kept separate.
A4: Metric | B4: Per site | C4: x Sites | D4: Network total | E4: Note
A5: Base EBITDA — Conservative | B5: ='Per_Site'!D16 | C5: =Inputs!$C$37 | D5: =B5*C5 | E5: BASE — defensible
A6: Base EBITDA — Upgraded | B6: ='Per_Site'!D17 | C6: =Inputs!$C$37 | D6: =B6*C6 | E6: BASE — needs distillation+offtake
A7: Signed-headline EBITDA (credit-dependent) | B7: ='Per_Site'!D18 | C7: =Inputs!$C$37 | D7: =B7*C7 | E7: CONTINGENT — ~$20.4M/site credits
A8: Signed-headline revenue | B8: ='Per_Site'!B18 | C8: =Inputs!$C$37 | D8: =B8*C8 | E8: CONTINGENT
A9: Contingent credit value at risk | B9: ='Per_Site'!B21 | C9: =Inputs!$C$37 | D9: =B9*C9 | E9: NOT secured
A10: Year 1 cash out | B10: ='Per_Site'!B27 | C10: =Inputs!$C$37 | D10: =B10*C10 | E10: capital
A11: Project raises (sites x $15M) | B11: ='Per_Site'!B24 | C11: =Inputs!$C$37 | D11: =B11*C11 | E11: excludes company raise

Sheet Raises
A1: The two raises — kept distinct
A2: Site capital != company capital. Never blend.
A4: Item | B4: Amount | C4: Note
A5: Project raise per site | B5: =Inputs!$C$26 | C5: site deployment
A6: Project raises — 3 sites | B6: =Inputs!$C$26*Inputs!$C$37 | C6: excludes company raise
A7: Company-level raise (separate) | B7: =Inputs!$C$36 | C7: working capital, payroll, PublicLogic gov fees, team buildout [CONFIRM split]
A8: Combined discussion envelope | B8: =Inputs!$C$26*Inputs!$C$37+Inputs!$C$36 | C8: present asks separately

Sheet Caveats
A1: Caveats & confirm-before-send
A2: Every contingent assumption and open item. Investor headline must lead with the base case.
A4: HEADLINE DISCIPLINE
A5: * Investor-facing headline = BASE EBITDA (fuel + carbon black). Show RIN + 45Z as separately-labeled contingent upside.
A6: * Signed-model EBITDA (~$30.2M/site) is ~$20.4M dependent on RIN + 45Z. Do NOT anchor the deck on it unproven.
A8: CONTINGENT / REGULATORY
A9: * D4/D7 RIN: requires EPA RFS pathway registration; volumes & prices [CONFIRM].
A10: * Section 45Z (RD + SAF): requires eligibility determination + tax counsel; rate assumption [CONFIRM].
A11: * SAF/kerosene product classification [CONFIRM] — drives both fuel revenue and 45Z.
A12: * Carbon black: included in base as a real product; price + offtake [CONFIRM]. (Signed model excluded it.)
A13: * OPEX IS UNDERSTATED IN THE SIGNED MODEL. The uploaded WasteWerx staffing pro forma shows 62 FTE / $5.52M loaded
A14: labor alone — more than the signed model's entire implied opex ($5.38M). Bottom-up opex (Opex_BuildUp sheet) is
... A33: Not financial, accounting, securities, or tax advice. Figures trace to the canonical workbook / signed pro forma; verify before use.
