Workbook

Sheet README
A1: PublicLogic — Top 10 Opportunities (Business Relationships)
A2: Live scored & ranked. Yellow = editable weights (Inputs). Date: 2026-06-03. Revenue figures are illustrative planning estimates from PublicLogic's own deal docs, not quotes.
A5: PURPOSE
A6: Prioritize the opportunities heading into PublicLogic's relationships with its business people —
A7: Robert McCall (EM&S / Michigan LTC Network), Glen Scharer (Carbon Alliance), WasteWerx, AED,
A8: Acadia Capital, CivicPlus, and the NMTC/CDE channel — so effort goes where the leverage is.
A10: SHEETS
A11: Inputs - scoring weights (edit to re-rank). Weights sum to 1.00.
A12: Top10 - the scored, ranked opportunities. Composite & Rank are live formulas.
A13: Revenue - PublicLogic fee potential per opportunity (near-12-month + lifetime). Live totals.
A14: Action - relationship owner, the move, fee structure, cost route, key flag, next step.
A16: HOW THE SCORE WORKS
... A25: Not legal/accounting/securities advice. Subject to funding source, approved budget, cost principles.

Sheet Inputs
A1: Inputs — scoring weights
A2: Edit the yellow weights to re-rank. They should sum to 1.00 (see check).
A4: Code | B4: Criterion | C4: Weight
A5: REV | B5: PublicLogic revenue potential (life of relationship) | C5: 0.2
A6: PROB | B6: Probability / readiness (closeness to signed) | C6: 0.22
A7: RECUR | B7: Recurrence (retainer / channel vs one-time) | C7: 0.16
A8: STRAT | B8: Strategic leverage (reference / channel / reuse) | C8: 0.16
A9: SPEED | B9: Speed to cash | C9: 0.14
A10: RISKADJ | B10: Risk-adjusted quality (clean vs securities/contingent/stall) | C10: 0.12
B11: SUM (must = 1.00) | C11: =SUM(C5:C10)

Sheet Top10
A1: Top 10 Opportunities — scored & ranked (live)
A2: Composite = weighted avg of the six 1-5 scores. Rank is live. Edit scores or weights to re-rank.
A4: # | B4: Opportunity | C4: Relationship / source | D4: REV | E4: PROB | F4: RECUR | G4: STRAT | H4: SPEED | I4: RISKADJ | J4: Composite | K4: Rank
A5: 1 | B5: Michigan LTC Network — Site 1 (EGLE invite -> build) | C5: Robert McCall / EM&S | D5: 5 | E5: 4 | F5: 4 | G5: 5 | H5: 4 | I5: 3 | J5: =D5*Inputs!$C$5+E5*Inputs!$C$6+F5*Inputs!$C$7+G5*Inputs!$C$8+H5*Inputs!$C$9+I5*Inputs!$C$10 | K5: =RANK(J5,$J$5:$J$14,0)
A6: 2 | B6: Michigan LTC Network — Sites 2-4 replication | C6: Robert McCall / EM&S | D6: 5 | E6: 3 | F6: 5 | G6: 5 | H6: 2 | I6: 3 | J6: =D6*Inputs!$C$5+E6*Inputs!$C$6+F6*Inputs!$C$7+G6*Inputs!$C$8+H6*Inputs!$C$9+I6*Inputs!$C$10 | K6: =RANK(J6,$J$5:$J$14,0)
A7: 3 | B7: WasteWerx portfolio MSA (governance across client base) | C7: JT Clark / WasteWerx | D7: 4 | E7: 3 | F7: 5 | G7: 5 | H7: 3 | I7: 4 | J7: =D7*Inputs!$C$5+E7*Inputs!$C$6+F7*Inputs!$C$7+G7*Inputs!$C$8+H7*Inputs!$C$9+I7*Inputs!$C$10 | K7: =RANK(J7,$J$5:$J$14,0)
A8: 4 | B8: NMTC governance practice via CDE channel (CEI, USBCDC) | C8: CEI / USBCDC / Lin Thornton | D8: 5 | E8: 3 | F8: 5 | G8: 5 | H8: 2 | I8: 3 | J8: =D8*Inputs!$C$5+E8*Inputs!$C$6+F8*Inputs!$C$7+G8*Inputs!$C$8+H8*Inputs!$C$9+I8*Inputs!$C$10 | K8: =RANK(J8,$J$5:$J$14,0)
A9: 5 | B9: Carbon Alliance deal-flow channel (ongoing) | C9: Glen Scharer | D9: 4 | E9: 3 | F9: 4 | G9: 5 | H9: 2 | I9: 4 | J9: =D9*Inputs!$C$5+E9*Inputs!$C$6+F9*Inputs!$C$7+G9*Inputs!$C$8+H9*Inputs!$C$9+I9*Inputs!$C$10 | K9: =RANK(J9,$J$5:$J$14,0)
A10: 6 | B10: La Porte, IN waste-to-energy (scope -> build) | C10: Glen Scharer | D10: 3 | E10: 3 | F10: 3 | G10: 4 | H10: 3 | I10: 4 | J10: =D10*Inputs!$C$5+E10*Inputs!$C$6+F10*Inputs!$C$7+G10*Inputs!$C$8+H10*Inputs!$C$9+I10*Inputs!$C$10 | K10: =RANK(J10,$J$5:$J$14,0)
A11: 7 | B11: AED / Pocomoke NMTC compliance module | C11: Brian Kuhn / Joe Loud | D11: 4 | E11: 2 | F11: 4 | G11: 3 | H11: 2 | I11: 3 | J11: =D11*Inputs!$C$5+E11*Inputs!$C$6+F11*Inputs!$C$7+G11*Inputs!$C$8+H11*Inputs!$C$9+I11*Inputs!$C$10 | K11: =RANK(J11,$J$5:$J$14,0)
A12: 8 | B12: City of Flint coordination engagement (Phase 1 -> retainer) | C12: via Robert McCall | D12: 3 | E12: 3 | F12: 4 | G12: 3 | H12: 3 | I12: 3 | J12: =D12*Inputs!$C$5+E12*Inputs!$C$6+F12*Inputs!$C$7+G12*Inputs!$C$8+H12*Inputs!$C$9+I12*Inputs!$C$10 | K12: =RANK(J12,$J$5:$J$14,0)
A13: 9 | B13: CivicPlus channel partnership (govtech) | C13: CivicPlus | D13: 4 | E13: 2 | F13: 5 | G13: 4 | H13: 1 | I13: 4 | J13: =D13*Inputs!$C$5+E13*Inputs!$C$6+F13*Inputs!$C$7+G13*Inputs!$C$8+H13*Inputs!$C$9+I13*Inputs!$C$10 | K13: =RANK(J13,$J$5:$J$14,0)
A14: 10 | B14: Acadia Capital referral channel | C14: Brien Walton / Acadia | D14: 2 | E14: 3 | F14: 3 | G14: 4 | H14: 3 | I14: 5 | J14: =D14*Inputs!$C$5+E14*Inputs!$C$6+F14*Inputs!$C$7+G14*Inputs!$C$8+H14*Inputs!$C$9+I14*Inputs!$C$10 | K14: =RANK(J14,$J$5:$J$14,0)
B16: Tip: sort by Rank (col K) to see the priority order. Highest composite = work it first.

Sheet Revenue
A1: PublicLogic fee potential per opportunity (illustrative)
A2: Near-12-month vs lifetime PublicLogic revenue. Estimates from PublicLogic's own deal docs — not quotes. Live totals.
A4: # | B4: Opportunity | C4: Near 12-mo ($) | D4: Lifetime ($) | E4: Basis / fee structure
A5: 1 | B5: Michigan LTC Network — Site 1 (EGLE invite -> build) | C5: 200000 | D5: 775000 | E5: $175K capitalized build + ~$10K/mo runtime + grant-stacking; 5-yr single-site ~$775K
A6: 2 | B6: Michigan LTC Network — Sites 2-4 replication | C6: 60000 | D6: 2250000 | E6: Sites 2-4 @ $75-100K build + $10K/mo each; network lifetime across 3 sites
A7: 3 | B7: WasteWerx portfolio MSA (governance across client base) | C7: 40000 | D7: 1500000 | E7: Portfolio MSA: per-client governance + runtime across WasteWerx deployments
A8: 4 | B8: NMTC governance practice via CDE channel (CEI, USBCDC) | C8: 25000 | D8: 2000000 | E8: Productized NMTC 7-yr compliance module repeated across CDE-financed deals
A9: 5 | B9: Carbon Alliance deal-flow channel (ongoing) | C9: 20000 | D9: 1000000 | E9: Glen as recurring connector: scoping retainers + builds across his pipeline
A10: 6 | B10: La Porte, IN waste-to-energy (scope -> build) | C10: 30000 | D10: 400000 | E10: La Porte scope -> grant study -> build + runtime
A11: 7 | B11: AED / Pocomoke NMTC compliance module | C11: 35000 | D11: 300000 | E11: AED: $5K setup + $5K/mo x24 + $18K/yr yrs3-7 + underwriting (if reactivated)
A12: 8 | B12: City of Flint coordination engagement (Phase 1 -> retainer) | C12: 25000 | D12: 250000 | E12: Flint Phase 1 $18-25K + $6.5-15K/mo retainer
A13: 9 | B13: CivicPlus channel partnership (govtech) | C13: 10000 | D13: 1500000 | E13: CivicPlus: per-client referral economics at scale (early)
A14: 10 | B14: Acadia Capital referral channel | C14: 0 | D14: 500000 | E14: Indirect: referred capital-stack deals via Acadia validation
B15: TOTAL (illustrative pipeline potential) | C15: =SUM(C5:C14) | D15: =SUM(D5:D14)

Sheet Action
A1: Action plan — the move, the route, the flag
A2: How to convert each opportunity. Keep every business-funded fee fixed & non-contingent on federal money.
A4: # | B4: Opportunity | C4: Cost-treatment route | D4: Key flag | E4: Next move (owner)
A5: 1 | B5: Michigan LTC Network — Site 1 (EGLE invite -> build) | C5: Capitalized dev soft cost in project budget | D5: Securities lane; 5% grant-stacking must be non-contingent on federal | E5: Chase EGLE 'Encouraged to Apply' (~6/1); if invited, lead 7/7 full apps
A6: 2 | B6: Michigan LTC Network — Sites 2-4 replication | C6: Same; per-site capitalized buildout | D6: Replication depends on Site 1 closing first | E6: Lock Site-1 close; template the buildout for Sites 2-4
A7: 3 | B7: WasteWerx portfolio MSA (governance across client base) | C7: Per-client governance + runtime | D7: Don't become a captive sub of one OEM | E7: Convert to a portfolio MSA / preferred-partner agreement (JT Clark)
A8: 4 | B8: NMTC governance practice via CDE channel (CEI, USBCDC) | C8: NMTC soft-costs line of each deal | D8: Keep underwriting fixed/non-contingent for federal pieces | E8: Open CEI (Rob Levin) + USBCDC (via Lin Thornton); productize the module
A9: 5 | B9: Carbon Alliance deal-flow channel (ongoing) | C9: Scoping retainer + per-deal soft cost | D9: Glen's deals are early/funding-contingent — front-load paid scoping | E9: Deliver capabilities workbook + La Porte scope; lock WasteWerx intro
A10: 6 | B10: La Porte, IN waste-to-energy (scope -> build) | C10: Scope -> grant study -> build | D10: Funding-contingent; keep PL fee non-contingent | E10: Send NDA + one-page scope; define grant-study deliverable
A11: 7 | B11: AED / Pocomoke NMTC compliance module | C11: Project cost in $806,502 soft-costs line | D11: STALLED on unresponsive sponsor; reconcile job counts | E11: Reactivate via Loud OR pursue biochar thesis through Glen's channel
A12: 8 | B12: City of Flint coordination engagement (Phase 1 -> retainer) | C12: Soft cost in capital stack at close | D12: Don't promise grant outcomes; stay out of PuddleJumper weeds | E12: Get the scoping call with the City's funding-stack owner
A13: 9 | B13: CivicPlus channel partnership (govtech) | C13: Partner/referral economics | D13: Early; define integration + referral split | E13: Define the CivicPlus partnership model and pilot a joint client
A14: 10 | B14: Acadia Capital referral channel | C14: n/a (referral) | D14: Pure leverage; protect PL independence | E14: Keep Walton as validator; ask for warm intros to other deals
