Workbook

Sheet Summary
A1: Swanzey Capital Workbook — Summary
A2: Fund the whole backlog with majority-vote reserves + outside money. No new bonds, no 3/5 votes.
A4: Metric | B4: Value
A5: Total capital backlog | B5: =Projects!$B$10
A6: Paid by state / SRF / grants | B6: =Projects!$C$10+Projects!$D$10+Projects!$E$10
A7: Non-property-tax share | B7: =(Projects!$C$10+Projects!$D$10+Projects!$E$10)/Projects!$B$10
A8: Local share (saved via reserves) | B8: =Projects!$F$10
A9: Local share % | B9: =Projects!$F$10/Projects!$B$10
A10: New bonds required | B10: 0
A11: Peak impact on a median home | B11: ='10-Year Plan'!L16
A13: Thesis
A14: Voter signals (why the financing fits)
A15: Reserves & tax credits — pass rate | B15: 78–90%
A16: Facility bonds passed (need 3/5) | B16: 0 of 2 — failed 2024 & 2026 with majorities
A17: Operating-budget support, 2011 → 2025 | B17: ~81% → 57%
A18: 2025 capital activity | B18: acquired West Swanzey water; funded SRF study; board 3→5

Sheet Projects
A1: Capital Backlog — Projects & Funding Stack
A2: Local share = Total − State/Federal aid − SRF/rates − Grants. Costs are planning estimates.
A4: Project | B4: Total cost | C4: State/Fed aid | D4: SRF / water rates | E4: Grants & forgiveness | F4: Local share | G4: Local % | H4: Primary funding path
A5: Public Works Facility | B5: 1200000 | C5: 0 | D5: 0 | E5: 0 | F5: =B5-C5-D5-E5 | G5: =F5/B5 | H5: RSA 35 capital reserve (pay-go by ~2031)
A6: Christian Hill Road Bridge | B6: 1000000 | C6: 800000 | D6: 0 | E6: 0 | F6: =B6-C6-D6-E6 | G6: =F6/B6 | H6: RSA 234 state bridge aid (80%) + bridge reserve (20%)
A7: Lower Winchester Street | B7: 750000 | C7: 270000 | D7: 0 | E7: 0 | F7: =B7-C7-D7-E7 | G7: =F7/B7 | H7: Highway block grant + roads reserve
A8: West Swanzey Water System | B8: 2075000 | C8: 0 | D8: 1600000 | E8: 475000 | F8: =B8-C8-D8-E8 | G8: =F8/B8 | H8: NHDES DWSRF (repaid by water rates) + grants/forgiveness
A9: Town Hall ADA Stairwell | B9: 250000 | C9: 0 | D9: 0 | E9: 125000 | F9: =B9-C9-D9-E9 | G9: =F9/B9 | H9: CDBG/accessibility grant + facilities reserve
A10: TOTAL | B10: =SUM(B5:B9) | C10: =SUM(C5:C9) | D10: =SUM(D5:D9) | E10: =SUM(E5:E9) | F10: =SUM(F5:F9) | G10: =F10/B10

Sheet Reserve Ladder
A1: Capital Reserve Ladder (RSA 35 — simple-majority votes)
A2: Annual deposits build the local share. No bonds, no 3/5 votes.
A4: Capital Reserve Fund | B4: Target annual deposit | C4: Funds | D4: Vote
A5: Public Works Facility | B5: 200000 | C5: the facility (pay-go by ~2031) | D5: majority
A6: Bridges | B6: 50000 | C6: Christian Hill 20% share (state pays 80%) | D6: majority
A7: Highway Reconstruction | B7: 100000 | C7: Lower Winchester St & roads | D7: majority
A8: Highway Equipment | B8: 90000 | C8: plow/fleet replacement cycle | D8: majority
A9: Fire Apparatus | B9: 70000 | C9: engine/tanker cycle | D9: majority
A10: Town Facilities (incl. ADA) | B10: 40000 | C10: Town Hall ADA, building renewal | D10: majority
A11: Technology & Records | B11: 20000 | C11: GIS, cyber, RSA 33-A retention | D11: majority
A12: Note | B12: Deposits shown are steady-state targets; the 10-Year Plan tab phases them.

Sheet 10-Year Plan
A1: Capital Reserve Deposit Schedule & Tax Impact
A2: Edit deposits; Total, net-new rate, and the impact on a typical home recompute from Assumptions.
A4: Year | B4: PW Facility | C4: Bridge | D4: Roads | E4: Hwy Equip | F4: Fire App. | G4: Facilities | H4: Tech | I4: Total deposits | J4: Net-new $ to raise | K4: Net-new rate /$1,000 | L4: Impact on median home
A5: 2027 | B5: 150000 | C5: 50000 | D5: 100000 | E5: 90000 | F5: 70000 | G5: 40000 | H5: 20000 | I5: =SUM(B5:H5) | J5: =I5-Assumptions!$B$7 | K5: =J5/(Assumptions!$B$5/1000) | L5: =K5*Assumptions!$B$6/1000
A6: 2028 | B6: 250000 | C6: 50000 | D6: 100000 | E6: 90000 | F6: 70000 | G6: 40000 | H6: 20000 | I6: =SUM(B6:H6) | J6: =I6-Assumptions!$B$7 | K6: =J6/(Assumptions!$B$5/1000) | L6: =K6*Assumptions!$B$6/1000
A7: 2029 | B7: 250000 | C7: 50000 | D7: 100000 | E7: 90000 | F7: 70000 | G7: 40000 | H7: 20000 | I7: =SUM(B7:H7) | J7: =I7-Assumptions!$B$7 | K7: =J7/(Assumptions!$B$5/1000) | L7: =K7*Assumptions!$B$6/1000
A8: 2030 | B8: 300000 | C8: 25000 | D8: 100000 | E8: 90000 | F8: 70000 | G8: 40000 | H8: 20000 | I8: =SUM(B8:H8) | J8: =I8-Assumptions!$B$7 | K8: =J8/(Assumptions!$B$5/1000) | L8: =K8*Assumptions!$B$6/1000
A9: 2031 | B9: 250000 | C9: 25000 | D9: 100000 | E9: 90000 | F9: 70000 | G9: 40000 | H9: 20000 | I9: =SUM(B9:H9) | J9: =I9-Assumptions!$B$7 | K9: =J9/(Assumptions!$B$5/1000) | L9: =K9*Assumptions!$B$6/1000
A10: 2032 | B10: 0 | C10: 25000 | D10: 100000 | E10: 90000 | F10: 70000 | G10: 40000 | H10: 20000 | I10: =SUM(B10:H10) | J10: =I10-Assumptions!$B$7 | K10: =J10/(Assumptions!$B$5/1000) | L10: =K10*Assumptions!$B$6/1000
A11: 2033 | B11: 0 | C11: 25000 | D11: 100000 | E11: 90000 | F11: 70000 | G11: 40000 | H11: 20000 | I11: =SUM(B11:H11) | J11: =I11-Assumptions!$B$7 | K11: =J11/(Assumptions!$B$5/1000) | L11: =K11*Assumptions!$B$6/1000
A12: 2034 | B12: 0 | C12: 25000 | D12: 100000 | E12: 90000 | F12: 70000 | G12: 40000 | H12: 20000 | I12: =SUM(B12:H12) | J12: =I12-Assumptions!$B$7 | K12: =J12/(Assumptions!$B$5/1000) | L12: =K12*Assumptions!$B$6/1000
A13: 2035 | B13: 0 | C13: 25000 | D13: 100000 | E13: 90000 | F13: 70000 | G13: 40000 | H13: 20000 | I13: =SUM(B13:H13) | J13: =I13-Assumptions!$B$7 | K13: =J13/(Assumptions!$B$5/1000) | L13: =K13*Assumptions!$B$6/1000
A14: 2036 | B14: 0 | C14: 25000 | D14: 100000 | E14: 90000 | F14: 70000 | G14: 40000 | H14: 20000 | I14: =SUM(B14:H14) | J14: =I14-Assumptions!$B$7 | K14: =J14/(Assumptions!$B$5/1000) | L14: =K14*Assumptions!$B$6/1000
K16: Peak impact on median home | L16: =MAX(L5:L14)

Sheet Bridge Aid Calc
A1: State Bridge Aid Calculator (RSA 234)
A2: Edit the bridge cost; the 80/20 split recomputes.
A4: Eligible bridge cost | B4: 1000000
A5: State share | B5: =Assumptions!$B$8
A6: State pays | B6: =B4*B5
A7: Town share (bank in Bridge reserve) | B7: =B4-B6
A9: Prerequisite: current biennial inspection; on NHDOT program list. Contingent on annual state appropriation.

Sheet Capital & Special Votes
A1: Capital & Special Warrant Votes — the historical pattern
A2: % YES computed. Note: reserves & credits clear easily; facility BONDS win majorities but die at the 3/5 wall.
A4: Year | B4: Art | C4: Topic | D4: Amount | E4: YES | F4: NO | G4: % YES | H4: Threshold | I4: Result
A5: 2015 | B5: 3 | C5: Capital / borrowing | E5: 578 | F5: 294 | G5: =E5/(E5+F5) | H5: 3/5 | I5: PASS
A6: 2023 | B6: 4 | C6: Capital reserve deposit | D6: 272000 | E6: 470 | F6: 178 | G6: =E6/(E6+F6) | H6: majority | I6: PASS
A7: 2023 | B7: 5 | C7: Capital reserve deposit | D7: 590000 | E7: 494 | F7: 141 | G7: =E7/(E7+F7) | H7: majority | I7: PASS
A8: 2023 | B8: 6 | C8: Capital reserve deposit | D8: 261976 | E8: 528 | F8: 112 | G8: =E8/(E8+F8) | H8: majority | I8: PASS
A9: 2023 | B9: 7 | C9: Fire Stations Capital Reserve | D9: 300000 | E9: 365 | F9: 268 | G9: =E9/(E9+F9) | H9: majority | I9: PASS (narrow)
A10: 2023 | B10: 10 | C10: All-Veterans tax credit | E10: 569 | F10: 67 | G10: =E10/(E10+F10) | H10: majority | I10: PASS
A11: 2024 | B11: — | C11: Bond / revolving fund | E11: 702 | F11: 582 | G11: =E11/(E11+F11) | H11: 3/5 | I11: FAIL
A12: 2024 | B12: — | C12: Capital (3/5) | E12: 821 | F12: 448 | G12: =E12/(E12+F12) | H12: 3/5 | I12: PASS
A13: 2025 | B13: 4 | C13: Water / infrastructure | D13: 3500000 | E13: 864 | F13: 529 | G13: =E13/(E13+F13) | H13: 3/5 | I13: PASS
A14: 2025 | B14: 6 | C14: DWSRF study (100% principal forgiveness) | D14: 100000 | E14: 998 | F14: 406 | G14: =E14/(E14+F14) | H14: majority | I14: PASS
A15: 2025 | B15: 12 | C15: Acquire West Swanzey water system | E15: 822 | F15: 553 | G15: =E15/(E15+F15) | H15: majority | I15: PASS
A16: 2025 | B16: 13 | C16: Ambulance Expendable Trust | D16: 100000 | E16: 1060 | F16: 350 | G16: =E16/(E16+F16) | H16: majority | I16: PASS
A17: 2025 | B17: 15 | C17: Increase Select Board 3→5 | E17: 740 | F17: 653 | G17: =E17/(E17+F17) | H17: majority | I17: PASS
A18: 2025 | B18: 16 | C18: Second polling location (petition) | E18: 673 | F18: 727 | G18: =E18/(E18+F18) | H18: majority | I18: FAIL
A19: 2026 | B19: 3 | C19: Public Works Facility ($1.2M) | D19: 1200000 | E19: 681 | F19: 485 | G19: =E19/(E19+F19) | H19: 3/5 | I19: FAIL
A20: 2026 | B20: — | C20: Repeal SB2 (return to floor meeting) | E20: 345 | F20: 809 | G20: =E20/(E20+F20) | H20: majority | I20: FAIL
C22: Pattern: every bond that needed 3/5 and failed (2024, 2026 facility) still won a MAJORITY. The town will save, not borrow.

Sheet Budget Votes
A1: Operating-Budget Votes by Town-Meeting Year
A2: As-voted margins; support has slid from ~80% to 57%. (2018 & 2020 tallies not machine-readable.)
A4: Year | B4: Operating (proposed) | C4: Default | D4: YES | E4: NO | F4: % YES
A5: 2012 | B5: 5747885 | C5: 5705757 | D5: 616 | E5: 153 | F5: =D5/(D5+E5)
A6: 2013 | B6: 5824380 | C6: 5812387 | D6: 436 | E6: 131 | F6: =D6/(D6+E6)
A7: 2014 | B7: 5888782 | C7: 5821465 | D7: 495 | E7: 118 | F7: =D7/(D7+E7)
A8: 2015 | B8: 6012393 | C8: 5852076 | D8: 673 | E8: 206 | F8: =D8/(D8+E8)
A9: 2016 | B9: 6262426 | C9: 6067144 | D9: 670 | E9: 311 | F9: =D9/(D9+E9)
A10: 2017 | B10: 6210799 | C10: 6222738 | D10: 352 | E10: 168 | F10: =D10/(D10+E10)
A11: 2018 | B11: 6210799 | C11: 6302525 | D11: — | E11: — | F11: n/a
A12: 2019 | B12: 6452435 | C12: 6122397 | D12: 606 | E12: 309 | F12: =D12/(D12+E12)
A13: 2020 | B13: 6303000 | C13: 6072735 | D13: — | E13: — | F13: n/a
A14: 2021 | B14: 6716500 | C14: 6439109 | D14: 637 | E14: 460 | F14: =D14/(D14+E14)
A15: 2022 | B15: 6902500 | C15: 6864706 | D15: 751 | E15: 262 | F15: =D15/(D15+E15)
A16: 2023 | B16: 7425000 | C16: 7468834 | D16: 388 | E16: 236 | F16: =D16/(D16+E16)
A17: 2024 | B17: 7961500 | C17: 7935699 | D17: 738 | E17: 530 | F17: =D17/(D17+E17)
A18: 2025 | B18: 8370000 | C18: 7935699 | D18: 800 | E18: 596 | F18: =D18/(D18+E18)
A19: 2026 | B19: 8939036 | C19: 8891785 | D19: — | E19: — | F19: n/a

Sheet Board Elections
A1: Select Board Elections & Turnover
A2: Candidate vote totals where reported; ~ = approximate. Rising volatility compounds administrator churn.
A4: Year | B4: Seat | C4: Winner | D4: Votes | E4: Notable challengers | F4: Signal
A5: 2022 | B5: 3-yr | C5: Sly Karasinski | D5: 672 | E5: strong / uncontested | F5: incumbent retained
A6: 2023 | B6: 3-yr | C6: Bill Hutwelker | D6: 394 | E6: Michael York 216 | F6: contested
A7: 2023 | B7: seat | C7: Victoria Reck Ames | D7: 442 | E7: Brandon Self 418 | F7: won by 24 — new face
A8: 2024 | B8: 3-yr | C8: James Tempesta | D8: 461 | E8: Ward 294, LaBelle 288, Thorne 105 | F8: crowded field
A9: 2026 | B9: 3-yr | C9: James Ward | D9: 545 | E9: Tatro 481, York 414 | F9: incumbents challenged
A10: 2026 | B10: 1-yr (new 5th) | C10: Alan Gross | D10: 678 | E10: Elizabeth Traynor 408 | F10: first 5th-seat race

Sheet Assumptions
A1: Assumptions — edit the amber cells
A2: Everything else recomputes. Replace placeholders with the Town's real MS-1 valuation when available.
A4: Input | B4: Value | C4: Note
A5: Total assessed valuation (MS-1) | B5: 978600000 | C5: Planning estimate — REPLACE with the Town's actual total assessed value
A6: Median home (assessed value) | B6: 300000 | C6: Used to translate the rate into a typical tax bill
A7: Capital already in today's rate | B7: 403000 | C7: Existing debt service (~$338K) + capital outlay (~$65K); the net-new impact is measured against this
A8: State Bridge Aid share (RSA 234) | B8: 0.8 | C8: State pays this share of an eligible town bridge
A9: Bond interest rate (if ever used) | B9: 0.04 | C9: Reference only — the plan uses $0 bonds
