Workbook

Sheet README
B2: CANONICAL FINANCIAL MODEL v2.0 — MICHIGAN LTC NETWORK
B4: BASIS Keyed line-for-line to the EXECUTED WasteWerx Model 3 License Pro Forma.
B5: No calibration, no memory. Every figure is a signed-document value or a formula
B6: over signed inputs. The Reconciliation tab ties to zero by construction.
B8: SUPERSEDES v1.x, built from memory. v1 overstated Year 1 (stacked all milestones + 9 mo
B9: monitoring) and understated the cost base (consolidated $1.1M opex placeholder).
B10: Both are corrected here from the Pro Forma's actual phasing and $5.38M opex lines.
B12: TIES TO Year 1 to WasteWerx $6,670,328 · Year 1 total cash out $7,622,828 ·
B13: Steady-state revenue $35,581,680 · Steady-state EBITDA $30,200,531 · Payback 0.25 yr.
B15: STRUCTURE License, not sale. Title stays with WasteWerx. NOT depreciable. 20-yr term +
B16: 5-yr auto-renewals. Early termination after Year 3: remaining current-year MAR
B17: plus 50% of next year's MAR. Customer is the producer and retains 100% of revenue.
... B26: carbon-black grade/price (Flag 1) and RFS/§45Z qualification (Flag 3). See Flags.

Sheet Governance Controls
B2: GOVERNANCE CONTROLS — MODEL CONTROL INSTRUMENT
B4: MODEL CONTROL
B5: Model | C5: Michigan LTC Network — Canonical Financial Model
B6: Version | C6: v2.0 — keyed to executed Pro Forma (supersedes v1.x calibrated)
B7: Status | C7: TIES TO EXECUTED PRO FORMA — diligence-grade reconciliation
B8: Control owner | C8: PublicLogic LLC — governance, compliance, documentation
B9: Basis of record | C9: Executed WasteWerx Model 3 License Pro Forma + Feedstock Yield Model
B10: Lock state | C10: Inputs are signed-document values. Open items are commercial (Flags 1, 3).
B11: Update cadence | C11: On any executed-document change, or before external circulation.
B12: Circulation rule | C12: No investor circulation until Flag 1 closes and Walton briefed on Flag 2.
B14: CHANGE LOG
B15: Version | C15: Date | D15: Change
B16: v1.x | C16: May 2026 | D16: Built from memory; required revenue calibration; Year 1 overstated, cost base understated — SUPERSEDED
B17: v2.0 | C17: May 2026 | D17: Rebuilt keyed line-for-line to executed Pro Forma. Zero calibration. All reconciliation deltas zero by construction. RD+SAF revenue split, real .38M opex structure, Pro Forma Year 1 phasing.
B19: DISTRIBUTION CONTROL
B20: Recipient | C20: Stage | D20: Receives this model?
B21: EGLE OCE (grant) | C21: LOI | D21: NO — LOIs only; model is not an LOI-stage artifact
B22: EGLE — Sanabria (regulatory) | C22: Pre-application | D22: NO — regulatory briefs only
B23: Full project team | C23: Internal | D23: YES — operating + grant-strategy package
B24: Acadia / Walton | C24: Pre-investor | D24: YES — with Flag 2 briefing, before investor numbers
B25: Prospective investors | C25: Diligence | D25: NOT UNTIL Flag 1 closes + Walton briefed on Flag 2
B28: This tab is the model control instrument. v2 ties to the signed Pro Forma; the only open items are commercial (carbon-black grade/price, RFS/45Z qualification), not modeling.

Sheet Assumptions
B2: ASSUMPTIONS — ALL FROM EXECUTED PRO FORMA (yellow = signed input)
B4: WASTEWERX LICENSE — PAYMENT SCHEDULE (signed)
B5: Design fee (credited to license) | C5: 50000 | D5: $ | E5: Pro Forma Payment Schedule, Phase 0
B6: Phase 1 — initial deposit (50%, net of design credit) | C6: 2700000 | D6: $ | E6: Payment Schedule, Phase 1
B7: Phase 2 — build progress (25%) | C7: 1375000 | D7: $ | E7: Payment Schedule, Phase 2
B8: Phase 3 — build complete (15%) | C8: 825000 | D8: $ | E8: Payment Schedule, Phase 3
B9: Phase 4 — delivery & handoff (10%) | C9: 550000 | D9: $ | E9: Payment Schedule, Phase 4
B10: Monthly monitoring fee | C10: 35000 | D10: $/mo | E10: Pro Forma; begins at commissioning (Month 8), CPI-indexed
B11: Year 1 monthly fee months (Month 8–12) | C11: 5 | D11: months | E11: Payment Schedule — 5 months in Year 1
B12: Production royalty | C12: 0.6 | D12: $/gal | E12: Pro Forma; greater of actual or MAR
B13: Year 1 royalty (partial, Months 9–12) | C13: 995328 | D13: $ | E13: Payment Schedule — 13,824 gpd × 30 × 4 mo × $0.60
B14: PRODUCTION — PRO FORMA EXHIBIT A
B15: Daily fuel production (RD 7,056 + SAF 6,768) | C15: 13824 | D15: gal/day | E15: Operating Costs / Exhibit A
B16: Operating days / year | C16: 340 | D16: days | E16: Exhibit A nameplate definition
B17: Renewable Diesel — daily | C17: 7056 | D17: gal/day | E17: Revenue Summary
B18: SAF / Kerosene — daily | C18: 6768 | D18: gal/day | E18: Revenue Summary
B19: REVENUE PRICING — PRO FORMA REVENUE SUMMARY (signed)
B20: RD wholesale gate price | C20: 2 | D20: $/gal | E20: Revenue Summary
B21: SAF wholesale gate price | C21: 4.5 | D21: $/gal | E21: Revenue Summary
B22: D4 RIN — RD | C22: 2 | D22: $/gal | E22: Revenue Summary (1.5 RIN/gal × ~$1.33)
B23: D7 RIN — SAF | C23: 4 | D23: $/gal | E23: Revenue Summary (cellulosic SAF)
B24: §45Z — RD | C24: 1 | D24: $/gal | E24: Revenue Summary (at favorable CI)
B25: §45Z — SAF (enhanced) | C25: 1.75 | D25: $/gal | E25: Revenue Summary (enhanced SAF)
B26: OPERATING COSTS — PRO FORMA OPERATING COSTS TAB (signed)
B27: Feedstock procurement & logistics | C27: 940032 | D27: $/yr | E27: Operating Costs ($0.20/gal)
B28: Utilities (net of self-fuel) | C28: 235008 | D28: $/yr | E28: Operating Costs ($0.05/gal)
B29: Fuel distribution & shipping | C29: 376013 | D29: $/yr | E29: Operating Costs ($0.08/gal)
B30: Operating labor (4 FTE + 1 manager) | C30: 425000 | D30: $/yr | E30: Operating Costs
B31: Insurance (GL + property) | C31: 65000 | D31: $/yr | E31: Operating Costs
B32: Permit renewals & compliance | C32: 25000 | D32: $/yr | E32: Operating Costs
B33: G&A overhead | C33: 75000 | D33: $/yr | E33: Operating Costs
B34: CUSTOMER CAPEX + CORRIDOR
B35: Customer-side capex (site, utilities, permits, WC) | C35: 952500 | D35: $ | E35: Capital Investment tab (incl. $102,500 permitting)
B36: Community profit share | C36: 0.1 | D36: of net | E36: Project commitment (EM&S/PL), contractual, locally directed
B37: Corridor sites | C37: 3 | D37: sites | E37: Lincoln · Flint · Coleman (Coldwater = Phase 2, excluded)
B38: Waste diverted per site | C38: 15000 | D38: tons/yr | E38: Project planning assumption (EM&S/PL); confirm w/ operators
B39: Headcount per site (existing + new) | C39: 30 | D39: FTE | E39: Project planning assumption (EM&S/PL); confirm w/ operators

Sheet WasteWerx Cost
B2: WASTEWERX COST — PER SITE (ties to Pro Forma Payment Schedule)
B4: Year 1 to WasteWerx | C4: Amount | D4: Basis
B5: License fee (Phases 1–4) | C5: =Assumptions!C6+Assumptions!C7+Assumptions!C8+Assumptions!C9 -> 5450000 | D5: Net of $50K design credit = $5,450,000
B6: Design fee (credited, shown for completeness) | C6: =Assumptions!C5 -> 50000 | D6: Credited into Phase 1; included in Y1 total
B7: Year 1 monthly fees (Months 8–12) | C7: =Assumptions!C10*Assumptions!C11 -> 175000 | D7: $35,000 × 5 months = $175,000
B8: Year 1 production royalty (Months 9–12) | C8: =Assumptions!C13 -> 995328 | D8: Pro Forma Payment Schedule = $995,328
B9: TOTAL YEAR 1 TO WASTEWERX | C9: =C5+C6+C7+C8 -> 6670328 | D9: Pro Forma reference: $6,670,328
B11: Steady-state to WasteWerx (Year 2+) | C11: Amount | D11: Basis
B12: Monthly monitoring (12 mo) | C12: =Assumptions!C10*12 -> 420000 | D12: $35,000 × 12 = $420,000
B13: Production royalty (actual at full production) | C13: =Revenue!C7*Assumptions!C12 -> 2820096 | D13: Annual gallons × $0.60 = $2,820,096
B14: TOTAL STEADY-STATE TO WASTEWERX | C14: =C12+C13 -> 3240096 | D14: Pro Forma reference: $3,240,096 (greater of actual or MAR)

Sheet Revenue
B2: REVENUE — RD + SAF (ties to Pro Forma Revenue Summary)
B4: Production volumes (steady state) | C4: Annual | D4: Basis
B5: Renewable Diesel (gal/yr) | C5: =Assumptions!C17*Assumptions!C16 -> 2399040 | D5: 7,056 × 340 = 2,399,040
B6: SAF / Kerosene (gal/yr) | C6: =Assumptions!C18*Assumptions!C16 -> 2301120 | D6: 6,768 × 340 = 2,301,120
B7: Total fuel (gal/yr) | C7: =C5+C6 -> 4700160 | D7: 4,700,160
B9: Revenue streams (steady state) | C9: Annual | D9: Basis
B10: RD fuel sales | C10: =C5*Assumptions!C20 -> 4798080 | D10: $2.00/gal
B11: SAF fuel sales | C11: =C6*Assumptions!C21 -> 10355040 | D11: $4.50/gal
B12: D4 RIN — RD | C12: =C5*Assumptions!C22 -> 4798080 | D12: $2.00/gal — Flag 3
B13: D7 RIN — SAF | C13: =C6*Assumptions!C23 -> 9204480 | D13: $4.00/gal — Flag 3
B14: §45Z — RD | C14: =C5*Assumptions!C24 -> 2399040 | D14: $1.00/gal — Flag 3
B15: §45Z — SAF (enhanced) | C15: =C6*Assumptions!C25 -> 4026960 | D15: $1.75/gal — Flag 3
B16: TOTAL ANNUAL REVENUE | C16: =SUM(C10:C15) -> 35581680 | D16: Pro Forma reference: $35,581,680
B17: Carbon black — UPSIDE (excluded from base) | C17: 0 | D17: PENDING — Flag 1. Not in base revenue.

Sheet Per-Site P&L
B2: PER-SITE P&L — STEADY STATE (ties to Pro Forma)
B4: Steady-state P&L | C4: Annual | D4: Source
B5: Total revenue (fuel + RIN + §45Z) | C5: =Revenue!C16 -> 35581680 | D5: Revenue tab — carbon black excluded
B6: WasteWerx fees (monitoring + royalty) | C6: ='WasteWerx Cost'!C14*-1 -> -3240096 | D6: $3,240,096
B7: Feedstock procurement & logistics | C7: =Assumptions!C27*-1 -> -940032 | D7: Pro Forma Operating Costs
B8: Utilities | C8: =Assumptions!C28*-1 -> -235008 | D8: Pro Forma Operating Costs
B9: Fuel distribution & shipping | C9: =Assumptions!C29*-1 -> -376013 | D9: Pro Forma Operating Costs
B10: Operating labor (4 FTE + manager) | C10: =Assumptions!C30*-1 -> -425000 | D10: Pro Forma Operating Costs
B11: Insurance | C11: =Assumptions!C31*-1 -> -65000 | D11: Pro Forma Operating Costs
B12: Permit renewals & compliance | C12: =Assumptions!C32*-1 -> -25000 | D12: Pro Forma Operating Costs
B13: G&A overhead | C13: =Assumptions!C33*-1 -> -75000 | D13: Pro Forma Operating Costs
B14: STEADY-STATE EBITDA | C14: =SUM(C5:C13) -> 30200531 | D14: Pro Forma reference: $30,200,531
B15: Community profit share (10% of EBITDA) | C15: =C14*Assumptions!C36*-1 -> -3020053.1 | D15: Contractual, locally directed
B16: Net after community share | C16: =C14+C15 -> 27180478
B18: Payback | C18: Value | D18: Basis
B19: Year 1 cash out (WasteWerx Y1 + customer capex) | C19: ='WasteWerx Cost'!C9+Assumptions!C35 -> 7622828 | D19: Pro Forma reference: $7,622,828
B20: Steady-state EBITDA | C20: =C14 -> 30200531 | D20: From P&L above
B21: Simple payback (years) | C21: =C19/C14 -> 0.25240709 | D21: Pro Forma reference: 0.25 yr

Sheet Corridor x3
B2: CORRIDOR ROLLUP — LINCOLN · FLINT · COLEMAN
B4: Metric | C4: Per site | D4: Lincoln | E4: Flint | F4: Coleman
B5: Steady-state revenue | C5: ='Per-Site P&L'!C5 -> 35581680 | D5: =$C5 -> 35581680 | E5: =$C5 -> 35581680 | F5: =$C5 -> 35581680
B6: Steady-state EBITDA | C6: ='Per-Site P&L'!C14 -> 30200531 | D6: =$C6 -> 30200531 | E6: =$C6 -> 30200531 | F6: =$C6 -> 30200531
B7: Community profit share | C7: ='Per-Site P&L'!C15*-1 -> 3020053.1 | D7: =$C7 -> 3020053.1 | E7: =$C7 -> 3020053.1 | F7: =$C7 -> 3020053.1
B8: Year 1 cash out | C8: ='Per-Site P&L'!C19 -> 7622828 | D8: =$C8 -> 7622828 | E8: =$C8 -> 7622828 | F8: =$C8 -> 7622828
B9: Waste diverted (tons/yr) | C9: =Assumptions!C38 -> 15000 | D9: =$C9 -> 15000 | E9: =$C9 -> 15000 | F9: =$C9 -> 15000
B10: Headcount (FTE) | C10: =Assumptions!C39 -> 30 | D10: =$C10 -> 30 | E10: =$C10 -> 30 | F10: =$C10 -> 30
B12: Corridor totals (x3) | C12: Amount
B13: Total steady-state revenue | C13: =SUM(D5:F5) -> 106745040
B14: Total steady-state EBITDA | C14: =SUM(D6:F6) -> 90601593
B15: Total community profit share | C15: =SUM(D7:F7) -> 9060159.3
B16: Total Year 1 cash out | C16: =SUM(D8:F8) -> 22868484
B17: Total waste diverted (tons/yr) | C17: =SUM(D9:F9) -> 45000 | D17: Corridor narrative: 45,000 tons
B18: Total headcount (FTE) | C18: =SUM(D10:F10) -> 90 | D18: Corridor narrative: 90 jobs

Sheet Flags
B2: OPEN ITEMS — COMMERCIAL, NOT MODELING
B4: # | C4: Item | D4: Resolution | E4: Status
B5: 1 | C5: Carbon black not in base revenue | D5: Confirm grade and contracted price (WasteWerx / Carbon Alliance). Upside line only until then. The Feedstock Yield Model rates tires at 32% carbon co-product, graphene-precursor grade — real, but uncontracted. | E5: PENDING
B6: 2 | C6: License not depreciable | D6: Title stays with WasteWerx; no transfer on dissolution. Tax/balance-sheet treatment differs from owned equipment. Brief Walton before investor numbers. | E6: BRIEF
B7: 3 | C7: RFS / §45Z qualification | D7: Revenue assumes qualifying RFS producer status and favorable §45Z CI. RINs + §45Z are ~$24.8M of the $35.6M. Phase 1 workstream — material if delayed. | E7: PHASE 1
B8: 4 | C8: Year 1 phasing modeled from Pro Forma | D8: v1 stacked all milestones + 9mo monitoring. Now modeled per Payment Schedule (monthly Month 8, royalty Month 9). Ties to $6,670,328. | E8: CLOSED

Sheet Reconciliation
B2: RECONCILIATION — MODEL vs EXECUTED PRO FORMA
B4: Line | C4: This model | D4: Pro Forma (signed) | E4: Delta
B5: Year 1 to WasteWerx | C5: ='WasteWerx Cost'!C9 -> 6670328 | D5: 6670328 | E5: =C5-D5 -> 0
B6: Year 1 total cash out | C6: ='Per-Site P&L'!C19 -> 7622828 | D6: 7622828 | E6: =C6-D6 -> 0
B7: Steady-state revenue | C7: =Revenue!C16 -> 35581680 | D7: 35581680 | E7: =C7-D7 -> 0
B8: Steady-state EBITDA | C8: ='Per-Site P&L'!C14 -> 30200531 | D8: 30200531 | E8: =C8-D8 -> 0
B9: Simple payback (yr) | C9: ='Per-Site P&L'!C21 -> 0.25240709 | D9: 0.25 | E9: =C9-D9 -> 0.0024070852
B11: Deltas are zero by construction — every figure is a signed-document value or a formula over
B12: signed inputs. v1's calibration is gone. This is the diligence-grade reconciliation.
