Workbook

Sheet Cover
A1: Michigan LTC Network — Resource Recovery Corridor
A2: Investor & Partner Workbook · to be read with the Private Investor Deck
A5: Basis of record | B5: Canonical Financial Model v2.0 — keyed line-for-line to the executed WasteWerx Model 3 License Pro Forma (mutual NDA 2026-05-18).
A6: Reading | B6: Every figure is a signed-document value or a formula over one. Economics shown as a reconciled range (signed Pro Forma vs operator-reality).
A7: Status | B7: Diligence-grade working set. Open items are commercial (carbon black, RFS/§45Z, staffing reconciliation, offtake), not modeling.
A8: Date | B8: 2026-06-05
A10: SECURITIES NOTICE | B10: This workbook is for confidential discussion with accredited investors only. It is NOT an offer to sell or a solicitation to buy securities. Any offering, if made, will be made only through definitive documents reviewed by securities counsel. Contains forward-looking projections that are not guarantees. PublicLogic LLC is the governance/documentation partner — NOT a placement agent, broker-dealer, or adviser; its fee is fixed and non-contingent.
A11: HANDLING | B11: Private & Confidential. Keep separate from EGLE/public grant materials. Do not publish proprietary WasteWerx process detail.

Sheet Assumptions
A1: Assumptions — signed-document values (Canonical v2.0)
A2: Yellow = editable. Revenue & Pro Forma opex are executed-Pro-Forma values; stress levers are the diligence swings.
A4: Key | B4: Item | C4: Value | D4: Source
A5: rd_sales | B5: RD fuel sales (2,399,040 gal x $2.00) | C5: 4798080 | D5: Canonical Revenue
A6: saf_sales | B6: SAF fuel sales (2,301,120 gal x $4.50) | C6: 10355040 | D6: Canonical Revenue
A7: d4_rin | B7: D4 RIN — RD | C7: 4798080 | D7: Canonical Revenue — contingent (RFS)
A8: d7_rin | B8: D7 RIN — SAF | C8: 9204480 | D8: Canonical Revenue — contingent (RFS)
A9: z45_rd | B9: Section 45Z — RD | C9: 2399040 | D9: Canonical Revenue — contingent
A10: z45_saf | B10: Section 45Z — SAF | C10: 4026960 | D10: Canonical Revenue — contingent
A11: cb | B11: Carbon black | C11: 0 | D11: $0 in executed Pro Forma (upside; deck implied ~$10.125M, uncontracted)
A12: ww_fees | B12: WasteWerx fees (monitoring $420k + royalty $2,820,096) | C12: 3240096 | D12: Canonical P&L
A13: feedstock_pf | B13: Feedstock — Pro Forma ($0.20/gal) | C13: 940032 | D13: Canonical P&L
A14: utilities | B14: Utilities ($0.05/gal) | C14: 235008 | D14: Canonical P&L
A15: distribution | B15: Fuel distribution & shipping ($0.08/gal) | C15: 376013 | D15: Canonical P&L
A16: labor_pf | B16: Operating labor — Pro Forma (4 FTE + manager) | C16: 425000 | D16: Canonical P&L
... A28: sites | B28: Sites in corridor | C28: 3 | D28: Lincoln/Flint/Coleman

Sheet Economics
A1: Per-site economics — reconciled range
A2: Keyed to Canonical v2.0. 'As signed' = Pro Forma (5-FTE). 'Operator-reality' = 62-FTE staffing + real feedstock.
A4: REVENUE (steady state)
A5: Stream | B5: $/yr | C5: Category
A6: Renewable diesel sales | B6: =Assumptions!$C$5 | C6: Base fuel
A7: SAF / kerosene sales | B7: =Assumptions!$C$6 | C7: Base fuel
A8: D4 RIN | B8: =Assumptions!$C$7 | C8: Contingent (RFS)
A9: D7 RIN | B9: =Assumptions!$C$8 | C9: Contingent (RFS)
A10: §45Z — RD | B10: =Assumptions!$C$9 | C10: Contingent
A11: §45Z — SAF | B11: =Assumptions!$C$10 | C11: Contingent
A12: Carbon black | B12: =Assumptions!$C$11 | C12: Upside (excluded)
A13: Base fuel (RD+SAF) | B13: =B6+B7
A14: Contingent credits (RIN+45Z) | B14: =B8+B9+B10+B11
A15: TOTAL REVENUE | B15: =B13+B14+B12
A17: OPERATING COST & EBITDA
B18: As signed (Pro Forma, 5 FTE) | C18: Operator-reality (62 FTE)
A19: Total operating cost | B19: =Assumptions!$C$12+Assumptions!$C$13+Assumptions!$C$14+Assumptions!$C$15+Assumptions!$C$16+Assumptions!$C$17+Assumptions!$C$18+Assumptions!$C$19 | C19: =Assumptions!$C$12+Assumptions!$C$23+Assumptions!$C$14+Assumptions!$C$15+Assumptions!$C$20*Assumptions!$C$21*Assumptions!$C$22+Assumptions!$C$17+Assumptions!$C$18+Assumptions!$C$19
A20: EBITDA — fuel + credits | B20: =B15-B19 | C20: =B15-C19
A21: EBITDA — base fuel only (no credits) | B21: =B13-B19 | C21: =B13-C19
A22: Year 1 cash out | B22: =Assumptions!$C$24 | C22: =Assumptions!$C$24
A23: Community share (10% of EBITDA) | B23: =B20*Assumptions!$C$27 | C23: =C20*Assumptions!$C$27
A25: THREE-SITE CORRIDOR (x sites)
A26: Metric | B26: As signed | C26: Operator-reality
A27: Total revenue | B27: =(B15)*Assumptions!$C$28 | C27: =(B15)*Assumptions!$C$28
A28: EBITDA (fuel+credits) | B28: =(B20)*Assumptions!$C$28 | C28: =(C20)*Assumptions!$C$28
A29: Year 1 cash out | B29: =(B22)*Assumptions!$C$28 | C29: =(B22)*Assumptions!$C$28
A31: Note: $20.4M of the $35.58M revenue is RIN/§45Z, contingent on EPA RFS registration. Carbon black is $0 in the base. The $30.2M EBITDA assumes Pro Forma 5-FTE staffing; operator-reality integrates the 62-FTE pro forma.

Sheet Capital & Raises
A1: Capital & the two raises
A2: Site capital and company capital are distinct asks — never blended.
A4: Item | B4: Amount | C4: Note
A5: Project raise per site | B5: =Assumptions!$C$25 | C5: sponsor headline
A6: Project raises — 3 sites | B6: =Assumptions!$C$25*Assumptions!$C$28 | C6: excludes company raise
A7: Company-level raise (separate) | B7: =Assumptions!$C$26 | C7: working capital, payroll, governance, team [CONFIRM split]
A8: Combined discussion total | B8: =Assumptions!$C$25*Assumptions!$C$28+Assumptions!$C$26 | C8: present separately
A9: Year 1 cash out per site | B9: =Assumptions!$C$24 | C9: CONFIRMED (WasteWerx $6,670,328 + capex $952,500)
A11: ROUGH PER-SITE USE OF FUNDS (sponsor)
A12: Build / core plant | B12: 8000000
A13: Added construction | B13: 1000000
A14: Pre-processing equipment | B14: 2000000
A15: Contingency / fees / payroll / training | B15: 5000000
A16: Rough subtotal | B16: =SUM(B12:B15)
A17: Gap vs $15M raise [CONFIRM] | B17: =Assumptions!$C$25-B16

Sheet Grant Stack
A1: Grant stack — non-dilutive fuel around the private raise
A2: Grants are readiness/de-risking lanes, kept DISTINCT from the securities offering. They do not replace the core raise.
A4: Lane | B4: Agency | C4: Best fit | D4: Current posture / status | E4: PublicLogic role
A5: MI Healthy Climate Challenge #4 — Go Big, Go Clean | B5: EGLE | C5: Corridor (planning study) | D5: LOIs submitted 5/19; full app due 7/7; carbon-credit research ineligible; needs ≥50% facility-decarb framing; confirm program status | E5: Grant-stacking + application
A6: NextCycle Michigan | B6: EGLE/MI | C6: All sites | D6: Active support ecosystem; award status [CONFIRM] | E6: Coordination
A7: EGLE Scrap Tire Market Development | B7: EGLE | C7: Equipment funding | D7: FY27 target; ~50% cost share — this lane CAN fund equipment | E7: Eligibility + application
A8: EPA Brownfield Cleanup & Assessment | B8: EPA | C8: Flint/Dort; Coldwater | D8: $500K–$2M; environmental-readiness / diligence support | E8: Readiness
A9: USDA REAP / B&I Guaranteed Loans | B9: USDA | C9: Coleman / rural sites | D9: Up to $1M grant / $25M guarantee; site eligibility [CONFIRM] | E9: Stacking
A10: NMTC / Opportunity Zone / EDA | B10: Treasury/EDA | C10: Flint / all sites | D10: Structuring + infrastructure lanes; tract/cycle checks remain | E10: Structuring
A11: §45Z / RIN (clean-fuel credits) | B11: IRS/EPA | C11: Operating sites | D11: POST-qualification upside (~$20.4M/yr); RFS registration + §45Z eligibility required — NOT banked base case | E11: Compliance / MRV
A13: Note: §45Z + RIN are the operating clean-fuel credits in the model. §45Q (carbon capture) is a different mechanism and is NOT banked here. Grant proceeds reduce net investor exposure; they are not part of the securities offering.

Sheet Caveats & Open Items
A1: Open items — commercial, not modeling
A3: # | B3: Item | C3: Severity | D3: Resolution / owner
A4: 1 | B4: Staffing reconciliation: Pro Forma 5 FTE ($425k) vs WasteWerx staffing pro forma 62 FTE ($5.52M) | C4: CRITICAL | D4: Confirm actual headcount (cross-trained middle); integrate into site model — Robert/Vinny/Glen
A5: 2 | B5: RFS / §45Z: $20,428,560 of revenue is registration-contingent | C5: CRITICAL | D5: EPA RFS pathway petition + §45Z qualification (Phase 1) — Glen/counsel
A6: 3 | B6: Carbon black = $0 in executed Pro Forma | C6: HIGH | D6: Confirm grade + contracted price before representing — Glen/WasteWerx
A7: 4 | B7: Feedstock swing: $940k (PF) vs $3.72M (deck) vs ~$1M (ERR $25/ton tipping) | C7: HIGH | D7: Resolve with ERR supply terms — Robert
A8: 5 | B8: Securities: $47.5M solicitation; return structure unreconciled ($14M vs $40M) | C8: CRITICAL | D8: Securities counsel + Reg D/PPM before any send — counsel; PL not placement agent
A9: 6 | B9: Site list: active set Lincoln/Flint/Coleman (LOIs); Coldwater = Phase 2 | C9: HIGH | D9: Align deck/workbook to submitted record — team
A10: 7 | B10: Community benefit %: 10% of EBITDA vs 10% of equity (differ by ~10x) | C10: MEDIUM | D10: Reconcile + encode in operating agreements — Robert/counsel
A11: 8 | B11: License not depreciable (title stays with WasteWerx); MAR Yr1 70%/Yr2+ 80% | C11: MEDIUM | D11: Brief Walton on tax treatment; SPV transfer terms — counsel
A12: 9 | B12: Use-of-funds ~$16M vs $15M raise | C12: LOW | D12: Reconcile which line absorbs ~$1M — Robert

Sheet Documents on File
A1: Documents & support on file
A2: Source-backed. Draft letters marked DRAFT; do not represent draft support as commitment.
A4: Document | B4: Party | C4: Date | D4: Status
A5: Executed WasteWerx License Pro Forma (Model 3) | B5: WasteWerx | C5: 2026-05 | D5: CONFIRMED (basis of model)
A6: WasteWerx Mutual NDA | B6: WasteWerx / PublicLogic | C6: 2026-05-18 | D6: EXECUTED
A7: WasteWerx Brochure (IP-Protected) | B7: WasteWerx | C7: 2026 | D7: ON FILE — CONFIDENTIAL (SRC-019)
A8: Letter of Support | B8: Geocycle (Paolo Carollo) | C8: 2026-01-26 | D8: ON FILE
A9: Letter of Support | B9: University of Arizona (Dr. Joel Cuello) | C9: 2026-02-10 | D9: ON FILE
A10: Advisory validation | B10: Acadia Capital (Brien Walton) | C10: 2026-05-08 | D10: ON FILE (validation, not committed financing)
A11: Feedstock supply (Dort Hwy) | B11: ERR Inc. | C11: 2026-05 | D11: 10-yr, 40,000 t/yr at $25/ton tipping
A12: EGLE LOIs — Lincoln / Flint / Coleman | B12: EM&S / PublicLogic | C12: 2026-05-19 | D12: SUBMITTED
A13: LOS — National Salvage / Lake State / Acadia / WasteWerx | B13: Partners | C13: 2026 | D13: DRAFT — mark draft, not commitment
